{
  "appPageId" : "b6cd5cd8-c829-4c8b-a9f9-a5910f5eb5f7",
  "componentName" : "siteforce:sldsOneColLayout",
  "id" : "76612c93-68d8-4017-bf20-7b7d7dea54c6",
  "label" : "Record Detail",
  "regions" : [ {
    "components" : [ {
      "componentAttributes" : {
        "recordId" : "{!recordId}"
      },
      "componentName" : "forceCommunity:recordHeadline",
      "id" : "4a685c3b-c412-4c9d-869c-a16eb2228bc8",
      "renderPriority" : "NEUTRAL",
      "renditionMap" : { },
      "type" : "component"
    } ],
    "id" : "46e939b3-6330-419e-9c20-33d1576b9827",
    "regionName" : "header",
    "type" : "region"
  }, {
    "components" : [ {
      "componentAttributes" : {
        "detailsTabLabel" : "Details",
        "discussionsTabLabel" : "Feed",
        "recordId" : "{!recordId}",
        "relatedTabLabel" : "Related",
        "tab1Type" : "details",
        "tab2Type" : "related",
        "tab3Type" : "chatter",
        "tab4Type" : "none",
        "timelineTabLabel" : "Activity"
      },
      "componentName" : "forceCommunity:recordHomeTabs",
      "id" : "0411d05e-3da0-4e26-aec0-b05195990cd4",
      "renderPriority" : "NEUTRAL",
      "renditionMap" : { },
      "type" : "component"
    } ],
    "id" : "d6d2bc36-039b-428b-a539-7cd9829a56d1",
    "regionName" : "content",
    "type" : "region"
  }, {
    "id" : "9908493f-4215-46ad-aed3-54a53b62c558",
    "regionName" : "footer",
    "type" : "region"
  }, {
    "components" : [ {
      "componentAttributes" : {
        "description" : "",
        "metaTags" : "",
        "title" : "{!Record._Object}: {!Record._Title}"
      },
      "componentName" : "forceCommunity:seoAssistant",
      "id" : "d59474f7-12f8-4fc6-924f-bbfad71873b0",
      "renditionMap" : { },
      "type" : "component"
    } ],
    "id" : "ce32e341-8ba3-493f-8cb9-535ca87a636c",
    "regionName" : "sfdcHiddenRegion",
    "type" : "region"
  } ],
  "themeLayoutType" : "Inner",
  "type" : "view",
  "viewType" : "detail"
}